gravitype/__init__.py
gravitype/app.py
gravitype/game.py
gravitype/utils.py
gravitype/widgets.py
gravitype/widgets/play_area.py
gravitype/widgets/status_bar.py
gravitype/widgets/typed_area.py
gravitype-0.2.0.dist-info/licenses/LICENSE
gravitype-0.2.0.dist-info/METADATA
gravitype-0.2.0.dist-info/WHEEL
gravitype-0.2.0.dist-info/entry_points.txt
gravitype-0.2.0.dist-info/top_level.txt
gravitype-0.2.0.dist-info/RECORD
