Metadata-Version: 2.4
Name: gravitype
Version: 0.2.0
Summary: a fast paced terminal typing game
Requires-Python: >=3.9
License-File: LICENSE
Requires-Dist: textual>=5.3.0
Requires-Dist: textual-dev>=1.7.0
Dynamic: license-file
